{
  "id": "1d56fadf-4bb5-4336-87af-1564c7bac61b",
  "course": {
    "id": "b41a4fbd-02a6-49bc-997d-80f708d73401",
    "name": "EECS 2500 - EECS Linear Data Structures",
    "institution": {
      "id": "dcf8a9ef-1480-475d-a437-bf36d6409b66",
      "name": "_",
      "Description": ""
    }
  },
  "campus": {
    "id": "7c11598d-d362-4ff0-b9a4-93824f4d946b",
    "name": "Main Campus",
    "description": "Main Campus",
    "location": "2801 W Bancroft St, Toledo, OH 43606"
  },
  "start": "2018-08-27",
  "end": "2018-12-14",
  "meetings": [
    {
      "id": "0a2f5c5f-a0b5-483d-acf0-e468931601a9",
      "offering": "1d56fadf-4bb5-4336-87af-1564c7bac61b",
      "day": "TUESDAY",
      "time": "14:30:00",
      "duration": "01:20:00",
      "room": "RH 1520"
    },
    {
      "id": "f2ebb40e-1965-4e15-8411-96720a1b1015",
      "offering": "1d56fadf-4bb5-4336-87af-1564c7bac61b",
      "day": "THURSDAY",
      "time": "14:30:00",
      "duration": "01:20:00",
      "room": "RH 1520"
    }
  ]
}